autodock/__init__.py
autodock/codecs.py
autodock/events.py
autodock/main.py
autodock/node.py
autodock/plugin.py
autodock/utils.py
autodock/version.py
autodock-0.0.2.dist-info/DESCRIPTION.rst
autodock-0.0.2.dist-info/entry_points.txt
autodock-0.0.2.dist-info/METADATA
autodock-0.0.2.dist-info/metadata.json
autodock-0.0.2.dist-info/RECORD
autodock-0.0.2.dist-info/top_level.txt
autodock-0.0.2.dist-info/WHEEL
autodock-0.0.2.dist-info/zip-safe
