Metadata-Version: 2.0
Name: autodock
Version: 0.0.2
Summary: Daemon for Docker Automation
Home-page: https://github.com/prologic/autodock
Author: James Mills
Author-email: James Mills, prologic at shortcircuit dot net dot au
License: MIT
Download-URL: https://github.com/prologic/autodock/archive/master.zip
Keywords: docker automation daemon
Platform: POSIX
Classifier: Development Status :: 3 - Alpha
Classifier: Environment :: Console
Classifier: Intended Audience :: Developers
Classifier: Intended Audience :: System Administrators
Classifier: License :: OSI Approved :: MIT License
Classifier: Natural Language :: English
Classifier: Operating System :: POSIX :: BSD
Classifier: Operating System :: POSIX :: Linux
Classifier: Operating System :: MacOS :: MacOS X
Classifier: Programming Language :: Python :: 2.6
Classifier: Programming Language :: Python :: 2.7
Classifier: Programming Language :: Python :: Implementation :: CPython
Classifier: Programming Language :: Python :: Implementation :: PyPy
Requires-Dist: circuits
Requires-Dist: docker-py
Requires-Dist: jsonrpc-requests
